{
  "_format": "hh-sol-cache-2",
  "files": {
    "D:\\Presentations\\blockchain\\final_project_2\\contracts\\Files.sol": {
      "lastModificationDate": 1713789683666,
      "contentHash": "a17c8df6e83c1c03461ff254c70ea8fa",
      "sourceName": "contracts/Files.sol",
      "solcConfig": {
        "version": "0.8.24",
        "settings": {
          "evmVersion": "paris",
          "optimizer": {
            "enabled": false,
            "runs": 200
          },
          "outputSelection": {
            "*": {
              "*": [
                "abi",
                "evm.bytecode",
                "evm.deployedBytecode",
                "evm.methodIdentifiers",
                "metadata"
              ],
              "": [
                "ast"
              ]
            }
          }
        }
      },
      "imports": [],
      "versionPragmas": [
        ">=0.7.0 <0.9.0"
      ],
      "artifacts": [
        "Files"
      ]
    }
  }
}
